[
  {
    "url": "/api/Alumno",
    "method": "GET"
  },
  {
    "url": "/api/Alumno",
    "method": "POST",
    "body": {
      "nombre": "string",
      "ppa": 100,
      "telefono": 700000,
      "registro": 100002
    }
  },
  {
    "url": "/api/Alumno/33366",
    "method": "PUT",
    "body": {
      "nombre": "string",
      "ppa": 100,
      "telefono": 700000,
      "registro": 100002
    }
  },
  {
    "url": "/api/Alumno/3",
    "method": "DELETE"
  },
  {
    "url": "/api/Alumno",
    "method": "GET"
  },
  {
    "url": "/api/Materia",
    "method": "POST",
    "body": {
      "credito": 5,
      "esElectiva": true,
      "nombre": "string",
      "sigla": "string"
    }
  },
  {
    "url": "/api/Materia/2",
    "method": "PUT",
    "body": {
      "credito": 1,
      "esElectiva": true,
      "nombre": "string",
      "sigla": "ASA"
    }
  },
  {
    "url": "/api/Materia/400",
    "method": "DELETE"
  }
]
