[
  {
    "url": "http://localhost:3000/api/carreras",
    "method": "GET"
  },
  {
    "url": "http://localhost:3000/api/carreras",
    "method": "POST",
    "body": {
      "nombre": "Ingeniería de Sistemas",
      "codigo": "ING-SIS-001"
    }
  },
  {
    "url": "http://localhost:3000/api/carreras/1",
    "method": "GET"
  },
  {
    "url": "http://localhost:3000/api/carreras/1",
    "method": "PATCH",
    "body": {
      "nombre": "Ingeniería en Sistemas Computacionales",
      "codigo": "ING-SIS-002"
    }
  }
]
